saltext/cli/__init__.py
saltext/cli/__main__.py
saltext/cli/templates.py
saltext/cli/version.py
saltext/cli/project/.coveragerc.j2
saltext/cli/project/.gitignore.j2
saltext/cli/project/.pre-commit-config.yaml.j2
saltext/cli/project/.pylintrc
saltext/cli/project/LICENSE.j2
saltext/cli/project/README.md.j2
saltext/cli/project/noxfile.py.j2
saltext/cli/project/pyproject.toml.j2
saltext/cli/project/setup.cfg.j2
saltext/cli/project/setup.py
saltext/cli/project/.github/workflows/test.yml.j2
saltext/cli/project/.pre-commit-hooks/check-cli-examples.py.j2
saltext/cli/project/.pre-commit-hooks/make-autodocs.py.j2
saltext/cli/project/docs/Makefile
saltext/cli/project/docs/all.rst.j2
saltext/cli/project/docs/conf.py.j2
saltext/cli/project/docs/index.rst.j2
saltext/cli/project/docs/make.bat
saltext/cli/project/docs/sitevars.rst
saltext/cli/project/docs/_static/.gitkeep
saltext/cli/project/docs/ref/.gitkeep
saltext/cli/project/requirements/base.txt.j2
saltext/cli/project/requirements/docs.in
saltext/cli/project/requirements/lint.in
saltext/cli/project/requirements/tests.in
saltext/cli/project/requirements/py3.5/docs.txt
saltext/cli/project/requirements/py3.5/lint.txt
saltext/cli/project/requirements/py3.5/tests.txt
saltext/cli/project/requirements/py3.6/docs.txt
saltext/cli/project/requirements/py3.6/lint.txt
saltext/cli/project/requirements/py3.6/tests.txt
saltext/cli/project/requirements/py3.7/docs.txt
saltext/cli/project/requirements/py3.7/lint.txt
saltext/cli/project/requirements/py3.7/tests.txt
saltext/cli/project/requirements/py3.8/docs.txt
saltext/cli/project/requirements/py3.8/lint.txt
saltext/cli/project/requirements/py3.8/tests.txt
saltext/cli/project/requirements/py3.9/docs.txt
saltext/cli/project/requirements/py3.9/lint.txt
saltext/cli/project/requirements/py3.9/tests.txt
saltext/cli/project/tests/__init__.py
saltext/cli/project/tests/conftest.py.j2
saltext/cli/project/tests/integration/__init__.py
saltext/cli/project/tests/integration/conftest.py
salt_extension-0.24.0.dist-info/LICENSE
salt_extension-0.24.0.dist-info/METADATA
salt_extension-0.24.0.dist-info/WHEEL
salt_extension-0.24.0.dist-info/entry_points.txt
salt_extension-0.24.0.dist-info/top_level.txt
salt_extension-0.24.0.dist-info/RECORD
