Metadata-Version: 2.1
Name: salt-extension
Version: 0.24.0
Summary: Tool to simplify the creation of a new salt extension
Home-page: https://saltproject.io
Author: Pedro Algarvio
Author-email: pedro@algarvio.me
License: Apache Software License 2.0
Project-URL: Source, https://github.com/saltstack/salt-extension
Project-URL: Tracker, https://github.com/saltstack/salt-extension/issues
Keywords: salt-extension
Platform: any
Classifier: Programming Language :: Python
Classifier: Programming Language :: Cython
Classifier: Programming Language :: Python :: 3
Classifier: Programming Language :: Python :: 3 :: Only
Classifier: Programming Language :: Python :: 3.7
Classifier: Programming Language :: Python :: 3.8
Classifier: Programming Language :: Python :: 3.9
Classifier: Programming Language :: Python :: 3.10
Classifier: Programming Language :: Python :: 3.11
Classifier: Programming Language :: Python :: 3.12
Classifier: Development Status :: 4 - Beta
Classifier: Intended Audience :: Developers
Classifier: License :: OSI Approved :: Apache Software License
Requires-Python: >=3.7
License-File: LICENSE
Requires-Dist: click
Requires-Dist: click-params
Requires-Dist: jinja2 >=2.11.3
Provides-Extra: tests
Requires-Dist: pytest >=7.2.0 ; extra == 'tests'
